{
  "version": 1,
  "month": "2026-08",
  "venue": "Longbourn",
  "slots": [
    {
      "id": "2026-07-10T08:00",
      "date": "2026-07-10",
      "time": "08:00",
      "enabled": true
    },
    {
      "id": "2026-07-10T09:00",
      "date": "2026-07-10",
      "time": "09:00",
      "enabled": false
    },
    {
      "id": "2026-07-10T10:30",
      "date": "2026-07-10",
      "time": "10:30",
      "enabled": true
    },
    {
      "id": "2026-07-10T11:45",
      "date": "2026-07-10",
      "time": "11:45",
      "enabled": true
    },
    {
      "id": "2026-07-10T13:00",
      "date": "2026-07-10",
      "time": "13:00",
      "enabled": false
    },
    {
      "id": "2026-07-17T08:00",
      "date": "2026-07-17",
      "time": "08:00",
      "enabled": false
    },
    {
      "id": "2026-07-17T09:00",
      "date": "2026-07-17",
      "time": "09:00",
      "enabled": false
    },
    {
      "id": "2026-07-17T10:30",
      "date": "2026-07-17",
      "time": "10:30",
      "enabled": true
    },
    {
      "id": "2026-07-17T11:45",
      "date": "2026-07-17",
      "time": "11:45",
      "enabled": true
    },
    {
      "id": "2026-07-17T13:00",
      "date": "2026-07-17",
      "time": "13:00",
      "enabled": false
    },
    {
      "id": "2026-07-24T08:00",
      "date": "2026-07-24",
      "time": "08:00",
      "enabled": false
    },
    {
      "id": "2026-07-24T09:00",
      "date": "2026-07-24",
      "time": "09:00",
      "enabled": false
    },
    {
      "id": "2026-07-24T10:30",
      "date": "2026-07-24",
      "time": "10:30",
      "enabled": true
    },
    {
      "id": "2026-07-24T11:45",
      "date": "2026-07-24",
      "time": "11:45",
      "enabled": true
    },
    {
      "id": "2026-07-24T13:00",
      "date": "2026-07-24",
      "time": "13:00",
      "enabled": false
    },
    {
      "id": "2026-07-31T08:00",
      "date": "2026-07-31",
      "time": "08:00",
      "enabled": false
    },
    {
      "id": "2026-07-31T09:00",
      "date": "2026-07-31",
      "time": "09:00",
      "enabled": false
    },
    {
      "id": "2026-07-31T10:30",
      "date": "2026-07-31",
      "time": "10:30",
      "enabled": true
    },
    {
      "id": "2026-07-31T11:45",
      "date": "2026-07-31",
      "time": "11:45",
      "enabled": true
    },
    {
      "id": "2026-07-31T13:00",
      "date": "2026-07-31",
      "time": "13:00",
      "enabled": false
    },
    {
      "id": "2026-08-07T08:00",
      "date": "2026-08-07",
      "time": "08:00",
      "enabled": false
    },
    {
      "id": "2026-08-07T09:00",
      "date": "2026-08-07",
      "time": "09:00",
      "enabled": false
    },
    {
      "id": "2026-08-07T10:30",
      "date": "2026-08-07",
      "time": "10:30",
      "enabled": true
    },
    {
      "id": "2026-08-07T11:45",
      "date": "2026-08-07",
      "time": "11:45",
      "enabled": true
    },
    {
      "id": "2026-08-07T13:00",
      "date": "2026-08-07",
      "time": "13:00",
      "enabled": false
    },
    {
      "id": "2026-08-14T08:00",
      "date": "2026-08-14",
      "time": "08:00",
      "enabled": false
    },
    {
      "id": "2026-08-14T09:00",
      "date": "2026-08-14",
      "time": "09:00",
      "enabled": false
    },
    {
      "id": "2026-08-14T10:30",
      "date": "2026-08-14",
      "time": "10:30",
      "enabled": true
    },
    {
      "id": "2026-08-14T11:45",
      "date": "2026-08-14",
      "time": "11:45",
      "enabled": true
    },
    {
      "id": "2026-08-14T13:00",
      "date": "2026-08-14",
      "time": "13:00",
      "enabled": false
    },
    {
      "id": "2026-08-21T08:00",
      "date": "2026-08-21",
      "time": "08:00",
      "enabled": false
    },
    {
      "id": "2026-08-21T09:00",
      "date": "2026-08-21",
      "time": "09:00",
      "enabled": false
    },
    {
      "id": "2026-08-21T10:30",
      "date": "2026-08-21",
      "time": "10:30",
      "enabled": true
    },
    {
      "id": "2026-08-21T11:45",
      "date": "2026-08-21",
      "time": "11:45",
      "enabled": true
    },
    {
      "id": "2026-08-21T13:00",
      "date": "2026-08-21",
      "time": "13:00",
      "enabled": false
    },
    {
      "id": "2026-08-28T08:00",
      "date": "2026-08-28",
      "time": "08:00",
      "enabled": false
    },
    {
      "id": "2026-08-28T09:00",
      "date": "2026-08-28",
      "time": "09:00",
      "enabled": false
    },
    {
      "id": "2026-08-28T10:30",
      "date": "2026-08-28",
      "time": "10:30",
      "enabled": true
    },
    {
      "id": "2026-08-28T11:45",
      "date": "2026-08-28",
      "time": "11:45",
      "enabled": true
    },
    {
      "id": "2026-08-28T13:00",
      "date": "2026-08-28",
      "time": "13:00",
      "enabled": false
    }
  ],
  "players": {
    "mike-ertl": {
      "name": "Mike Ertl"
    },
    "phil-charles": {
      "name": "Phil Charles"
    },
    "akiko": {
      "name": "Akiko"
    },
    "arda": {
      "name": "Arda"
    },
    "chris-danzinger": {
      "name": "Chris Danziger"
    },
    "chris-dalley": {
      "name": "Chris Dalley"
    },
    "ellen": {
      "name": "Ellen"
    },
    "jude-zur": {
      "name": "Jude Zur"
    },
    "michael-w-m": {
      "name": "Michael W-M"
    },
    "peter-miell": {
      "name": "Peter Miell"
    },
    "rachel": {
      "name": "Rachel"
    },
    "jo-tr": {
      "name": "Jo TR"
    },
    "richard-moxon": {
      "name": "Richard Moxon"
    },
    "david-taylor": {
      "name": "David Taylor"
    },
    "ian-thomas": {
      "name": "Ian Thomas"
    },
    "gina-williams": {
      "name": "Gina Williams"
    },
    "anthea": {
      "name": "Anthea"
    }
  },
  "availability": {
    "mike-ertl": {
      "green": [
        "2026-08-07T11:45",
        "2026-08-14T11:45",
        "2026-08-21T11:45"
      ],
      "yellow": [],
      "updatedAt": "2026-07-09T18:21:16.717Z"
    },
    "jo-tr": {
      "green": [],
      "yellow": [
        "2026-08-28T10:30"
      ],
      "updatedAt": "2026-07-13T09:15:30.398Z"
    },
    "david-taylor": {
      "green": [
        "2026-08-07T10:30",
        "2026-08-21T10:30",
        "2026-08-28T10:30"
      ],
      "yellow": [],
      "updatedAt": "2026-07-14T18:33:31.247Z"
    },
    "chris-dalley": {
      "green": [
        "2026-08-07T10:30",
        "2026-08-14T10:30",
        "2026-08-14T11:45",
        "2026-08-21T10:30",
        "2026-08-21T11:45",
        "2026-08-28T10:30",
        "2026-08-28T11:45"
      ],
      "yellow": [],
      "updatedAt": "2026-07-17T10:53:51.199Z"
    }
  },
  "allocations": {
    "2026-07-10T08:00": {
      "players": [
        "mike-ertl",
        "chris-danzinger",
        "arda",
        "richard-moxon"
      ],
      "yellowCandidates": [],
      "confirmed": [
        "mike-ertl",
        "chris-danzinger",
        "arda",
        "richard-moxon"
      ]
    },
    "2026-07-17T11:45": {
      "players": [
        "mike-ertl",
        "arda",
        "michael-w-m",
        "chris-danzinger"
      ],
      "yellowCandidates": [],
      "confirmed": [
        "mike-ertl",
        "arda",
        "michael-w-m",
        "chris-danzinger"
      ]
    },
    "2026-07-17T10:30": {
      "players": [
        "richard-moxon",
        "david-taylor",
        "jo-tr",
        "phil-charles"
      ],
      "yellowCandidates": [],
      "confirmed": [
        "richard-moxon",
        "david-taylor",
        "jo-tr",
        "phil-charles"
      ]
    },
    "2026-07-24T10:30": {
      "players": [
        "anthea",
        "david-taylor",
        "chris-dalley"
      ],
      "yellowCandidates": [],
      "confirmed": [
        "anthea",
        "david-taylor",
        "chris-dalley"
      ]
    },
    "2026-07-24T11:45": {
      "players": [
        "mike-ertl",
        "phil-charles",
        "ellen",
        "peter-miell"
      ],
      "yellowCandidates": [],
      "confirmed": [
        "mike-ertl",
        "phil-charles",
        "ellen",
        "peter-miell"
      ]
    },
    "2026-07-31T10:30": {
      "players": [
        "chris-dalley",
        "richard-moxon",
        "phil-charles",
        "david-taylor"
      ],
      "yellowCandidates": [],
      "confirmed": [
        "chris-dalley",
        "richard-moxon",
        "phil-charles",
        "david-taylor"
      ]
    },
    "2026-07-31T11:45": {
      "players": [
        "akiko",
        "mike-ertl",
        "arda",
        "phil-charles"
      ],
      "yellowCandidates": [],
      "confirmed": [
        "akiko",
        "mike-ertl",
        "arda",
        "phil-charles"
      ]
    },
    "2026-07-10T10:30": {
      "players": [],
      "yellowCandidates": [],
      "confirmed": []
    }
  },
  "allocatedMonths": {
    "2026-07": {
      "allocatedAt": "2026-07-17T10:46:48.657Z",
      "allocatedBy": "david-taylor",
      "automatic": false
    }
  },
  "changes": [
    {
      "type": "allocation-add",
      "text": "Added David Taylor to 2026-07-17T10:30",
      "at": "2026-07-09T16:54:19.021Z"
    },
    {
      "type": "allocation-add",
      "text": "Added Jo TR to 2026-07-17T10:30",
      "at": "2026-07-09T16:54:31.746Z"
    },
    {
      "type": "allocation-add",
      "text": "Added Phil Charles to 2026-07-17T10:30",
      "at": "2026-07-09T16:54:36.134Z"
    },
    {
      "type": "allocation-add",
      "text": "Added Chris Dalley to 2026-07-17T11:45",
      "at": "2026-07-09T16:54:56.892Z"
    },
    {
      "type": "allocation-add",
      "text": "Added Arda to 2026-07-17T11:45",
      "at": "2026-07-09T16:55:12.963Z"
    },
    {
      "type": "allocation-add",
      "text": "Added Phil Charles to 2026-07-17T11:45",
      "at": "2026-07-09T16:55:20.801Z"
    },
    {
      "type": "allocation-add",
      "text": "Added Anthea to 2026-07-24T10:30",
      "at": "2026-07-09T16:57:05.233Z"
    },
    {
      "type": "allocation-add",
      "text": "Added David Taylor to 2026-07-24T10:30",
      "at": "2026-07-09T16:57:10.283Z"
    },
    {
      "type": "allocation-add",
      "text": "Added Chris Dalley to 2026-07-24T10:30",
      "at": "2026-07-09T16:57:17.092Z"
    },
    {
      "type": "allocation-add",
      "text": "Added Phil Charles to 2026-07-24T10:30",
      "at": "2026-07-09T16:57:36.962Z"
    },
    {
      "type": "allocation-add",
      "text": "Added Akiko to 2026-07-24T11:45",
      "at": "2026-07-09T16:57:54.412Z"
    },
    {
      "type": "allocation-add",
      "text": "Added Mike Ertl to 2026-07-24T11:45",
      "at": "2026-07-09T16:58:00.821Z"
    },
    {
      "type": "allocation-add",
      "text": "Added Arda to 2026-07-24T11:45",
      "at": "2026-07-09T16:58:07.996Z"
    },
    {
      "type": "allocation-add",
      "text": "Added Phil Charles to 2026-07-24T11:45",
      "at": "2026-07-09T16:58:12.817Z"
    },
    {
      "type": "allocation-add",
      "text": "Added Chris Dalley to 2026-07-31T10:30",
      "at": "2026-07-09T16:58:33.137Z"
    },
    {
      "type": "allocation-add",
      "text": "Added Jo TR to 2026-07-31T10:30",
      "at": "2026-07-09T16:58:42.170Z"
    },
    {
      "type": "allocation-add",
      "text": "Added David Taylor to 2026-07-31T10:30",
      "at": "2026-07-09T16:58:49.499Z"
    },
    {
      "type": "allocation-add",
      "text": "Added Richard Moxon to 2026-07-31T10:30",
      "at": "2026-07-09T16:58:57.975Z"
    },
    {
      "type": "allocation-add",
      "text": "Added Akiko to 2026-07-31T11:45",
      "at": "2026-07-09T16:59:47.375Z"
    },
    {
      "type": "allocation-add",
      "text": "Added Mike Ertl to 2026-07-31T11:45",
      "at": "2026-07-09T16:59:52.217Z"
    },
    {
      "type": "allocation-add",
      "text": "Added Arda to 2026-07-31T11:45",
      "at": "2026-07-09T16:59:57.230Z"
    },
    {
      "type": "allocation-add",
      "text": "Added Phil Charles to 2026-07-31T11:45",
      "at": "2026-07-09T17:00:02.684Z"
    },
    {
      "type": "slot-removed",
      "text": "Removed 2026-08-28T13:00",
      "at": "2026-07-09T17:00:18.546Z"
    },
    {
      "type": "slot-removed",
      "text": "Removed 2026-08-28T10:30",
      "at": "2026-07-09T17:00:22.605Z"
    },
    {
      "type": "slot-removed",
      "text": "Removed 2026-08-28T08:00",
      "at": "2026-07-09T17:00:25.913Z"
    },
    {
      "type": "slot-removed",
      "text": "Removed 2026-08-07T08:00",
      "at": "2026-07-09T17:01:04.517Z"
    },
    {
      "type": "slot-removed",
      "text": "Removed 2026-08-07T10:30",
      "at": "2026-07-09T17:01:06.375Z"
    },
    {
      "type": "slot-removed",
      "text": "Removed 2026-08-14T08:00",
      "at": "2026-07-09T17:01:08.508Z"
    },
    {
      "type": "slot-removed",
      "text": "Removed 2026-08-14T11:45",
      "at": "2026-07-09T17:01:10.592Z"
    },
    {
      "type": "slot-removed",
      "text": "Removed 2026-08-14T10:30",
      "at": "2026-07-09T17:01:12.871Z"
    },
    {
      "type": "slot-removed",
      "text": "Removed 2026-08-07T11:45",
      "at": "2026-07-09T17:01:51.605Z"
    },
    {
      "type": "slot-removed",
      "text": "Removed 2026-08-21T10:30",
      "at": "2026-07-09T17:01:55.387Z"
    },
    {
      "type": "slot-removed",
      "text": "Removed 2026-08-28T11:45",
      "at": "2026-07-09T17:01:57.705Z"
    },
    {
      "type": "slot-removed",
      "text": "Removed 2026-08-21T11:45",
      "at": "2026-07-09T17:02:29.829Z"
    },
    {
      "type": "availability",
      "text": "Saved availability for Mike Ertl",
      "at": "2026-07-09T17:04:37.187Z"
    },
    {
      "type": "availability",
      "text": "Saved availability for Mike Ertl",
      "at": "2026-07-09T17:06:44.386Z"
    },
    {
      "type": "month-created",
      "text": "Created 2026-08",
      "at": "2026-07-09T17:07:21.069Z"
    },
    {
      "type": "availability",
      "text": "Saved availability for Mike Ertl",
      "at": "2026-07-09T18:21:16.718Z"
    },
    {
      "type": "allocation-add",
      "text": "Added Mike Ertl to 2026-07-10T10:30",
      "at": "2026-07-10T06:15:29.068Z"
    },
    {
      "type": "allocation-remove",
      "text": "Removed Mike Ertl from 2026-07-10T10:30",
      "at": "2026-07-10T06:15:40.211Z"
    },
    {
      "type": "allocation-remove",
      "text": "Removed Phil Charles from 2026-07-24T10:30",
      "at": "2026-07-10T13:47:27.070Z"
    },
    {
      "type": "allocation-remove",
      "text": "Removed Phil Charles from 2026-07-17T11:45",
      "at": "2026-07-10T13:47:56.560Z"
    },
    {
      "type": "allocation-add",
      "text": "Added Michael W-M to 2026-07-17T11:45",
      "at": "2026-07-10T13:55:27.763Z"
    },
    {
      "type": "allocation-add",
      "text": "Added Rachel to 2026-07-24T10:30",
      "at": "2026-07-10T13:55:49.875Z"
    },
    {
      "type": "allocation-remove",
      "text": "Removed Akiko from 2026-07-24T11:45",
      "at": "2026-07-10T14:01:21.811Z"
    },
    {
      "type": "allocation-add",
      "text": "Added Ellen to 2026-07-24T11:45",
      "at": "2026-07-10T14:01:50.701Z"
    },
    {
      "type": "availability",
      "text": "Saved availability for Jo TR",
      "at": "2026-07-13T09:15:30.398Z"
    },
    {
      "type": "allocation-remove",
      "text": "Removed Jo TR from 2026-07-31T10:30",
      "at": "2026-07-13T19:40:31.827Z"
    },
    {
      "type": "allocation-add",
      "text": "Added Phil Charles to 2026-07-31T10:30",
      "at": "2026-07-14T07:49:34.260Z"
    },
    {
      "type": "availability",
      "text": "Saved availability for David Taylor",
      "at": "2026-07-14T18:33:31.248Z"
    },
    {
      "type": "allocation-remove",
      "text": "Removed Phil Charles from 2026-07-31T10:30",
      "at": "2026-07-16T07:24:27.874Z"
    },
    {
      "type": "allocation-add",
      "text": "Added Phil Charles to 2026-07-31T10:30",
      "at": "2026-07-16T07:27:06.648Z"
    },
    {
      "type": "allocation-remove",
      "text": "Removed Chris Dalley from 2026-07-17T11:45",
      "at": "2026-07-16T09:37:06.784Z"
    },
    {
      "type": "allocation-add",
      "text": "Added Chris Danziger to 2026-07-17T11:45",
      "at": "2026-07-16T10:35:41.059Z"
    },
    {
      "type": "allocation-remove",
      "text": "Removed Arda from 2026-07-24T11:45",
      "at": "2026-07-17T07:50:17.185Z"
    },
    {
      "type": "allocation-add",
      "text": "Added Peter Miell to 2026-07-24T11:45",
      "at": "2026-07-17T08:09:46.551Z"
    },
    {
      "type": "allocation-remove",
      "text": "Removed David Taylor from 2026-07-31T10:30",
      "at": "2026-07-17T10:46:45.934Z"
    },
    {
      "type": "allocation-add",
      "text": "Added David Taylor to 2026-07-31T10:30",
      "at": "2026-07-17T10:46:48.657Z"
    },
    {
      "type": "availability",
      "text": "Saved availability for Chris Dalley",
      "at": "2026-07-17T10:53:51.200Z"
    },
    {
      "type": "allocation-remove",
      "text": "Removed Rachel from 2026-07-24T10:30",
      "at": "2026-07-18T14:06:28.193Z"
    }
  ],
  "updatedAt": "2026-07-18T14:06:28.195Z",
  "updatedBy": "mike-ertl",
  "manualEditedAt": "2026-07-18T14:06:28.190Z"
}
